{
    "Bank Information": {
        "Bank Name": "State Bank of India",
        "SWIFT/BIC": "SBININBB388",
        "Address": "City Branch, Madhuri Palace",
        "City": "Dhanbad",
        "Postal Code": "826001",
        "Bank Country": "India",
        "Recipient Account Number": "37061569256",
        "Indian Financial System Code (IFSC)": "SBIN0006948",
        "Message to Recipient Bank": "None",
        "Recipient Type": "Individual",
        "Main Currency": "Indian Rupee (INR)"
    },
    "Recipient Information": {
        "Recipient Country": "India",
        "Recipient Name": "Milind Kumar Mishra",
        "Recipient Nickname": "Milind Kumar Mishra",
        "Address": "Shiv Kripa Apartments, Housing Colony, Bartand",
        "City": "Dhanbad",
        "Province/Region": "Jharkhand",
        "Message to Recipient": "Payment",
        "Wire Recipient Group (Optional)": "Ungrouped"
    }
}
